kala/__init__.py
kala-0.1.0.dist-info/WHEEL
kala-0.1.0.dist-info/METADATA
kala-0.1.0.dist-info/RECORD
