Metadata-Version: 2.1
Name: kala
Version: 0.1.0
Summary: 
Author: Tomas Pereira de Vasconcelos
Author-email: tomasvasconcelos1@gmail.com
Requires-Python: >=3.8,<4.0
Classifier: Programming Language :: Python :: 3
Classifier: Programming Language :: Python :: 3.8
Requires-Dist: numpy (>=1.19.1,<2.0.0)
Requires-Dist: pandas (>=1.1.0,<2.0.0)
